Workbook

Sheet video description
A1: 标题 | B1: 创作者 | C1: 难度 | D1: 封面 | E1: tags | F1: 链接 | G1: 简介 | H1: 时长
A2: ETF einfach erklärt | B2: explainity® Erklärvideo | C2: B2 | E2: [“金融“，“投资”， “书面表达”，“explainity Erklärvideo”] | F2: https://pan.quark.cn/s/261eb9183ae3 | G2: ETF（交易所交易基金）就像股票、基金或房地产一样是一种投资的选择。本视频将解释它们究竟是什么。【投资有风险，本视频仅作科普与学习用途，不涉及任何投资建议】 | H2: 3min

Sheet subtitle
A1: 开始时间 | B1: 结束时间 | C1: 德文 | D1: 中文 | E1: ID
A2: 00:00:00,366 | B2: 00:00:03,466 | C2: Michael ist Besitzer einer Limonadenfabrik. | D2: Michael 是一家汽水工厂的老板。 | E2: ==ROW()-1 -> 1
A3: 00:00:03,566 | B3: 00:00:07,666 | C3: Mit seiner „Zitrus AG“ ist er vor 10 Jahren an die Börse gegangen | D3: 10 年前，他的“Zitrus 股份公司”成功上市。 | E3: ==ROW()-1 -> 2
A4: 00:00:07,766 | B4: 00:00:11,500 | C4: und seit neuestem auch im weltweiten Frucht-ETF vertreten. | D4: 而最近，这家公司也被纳入了全球水果 ETF。 | E4: ==ROW()-1 -> 3
A5: 00:00:11,933 | B5: 00:00:15,100 | C5: ETF steht für „Exchange Traded Fund“ | D5: ETF 是“交易型开放式指数基金”的缩写。 | E5: ==ROW()-1 -> 4
A6: 00:00:15,200 | B6: 00:00:18,033 | C6: oder auf deutsch „börsengehandelter Fonds“ | D6: 用德语来说，就是“在交易所交易的基金”。 | E6: ==ROW()-1 -> 5
A7: 00:00:18,133 | B7: 00:00:23,033 | C7: Für Menschen wie Susanne ist es eine Möglichkeit ihr Geld anzulegen. | D7: 对像 Susanne 这样的人来说，这是一个投资理财的方式。 | E7: ==ROW()-1 -> 6
A8: 00:00:23,800 | B8: 00:00:28,300 | C8: Ein ETF bündelt mehrere Anlageprodukte aus einem Bereich | D8: ETF 会把同一领域的多种投资产品集中在一起， | E8: ==ROW()-1 -> 7
A9: 00:00:28,400 | B9: 00:00:30,500 | C9: und bildet deren Index ab | D9: 并展现（追踪）它们的指数。 | E9: ==ROW()-1 -> 8
A10: 00:00:30,500 | B10: 00:00:34,233 | C10: Das ist der durchschnittliche Kurswert aller Produkte. | D10: 这个指数代表了所有产品的平均价格水平。 | E10: ==ROW()-1 -> 9
A11: 00:00:34,333 | B11: 00:00:36,900 | C11: Es gibt ETFs für den Aktienmarkt, | D11: 有针对股票市场的 ETF， | E11: ==ROW()-1 -> 10
A12: 00:00:36,900 | B12: 00:00:40,033 | C12: für Anleihen, Rohstoffe oder sogar Immobilien. | D12: 也有针对债券、原材料，甚至房地产的 ETF。 | E12: ==ROW()-1 -> 11
A13: 00:00:40,133 | B13: 00:00:44,400 | C13: Einige decken nur nachhaltige oder soziale Anlagen ab; | D13: 有些 ETF 只涵盖可持续或社会责任投资； | E13: ==ROW()-1 -> 12
... A54: 00:03:29,266 | B54: 00:03:33,466 | C54: und über den Erfolg seines einst kleinen Saftladens. | D54: 也为自己曾经的小果汁店取得的成功感到骄傲。 | E54: ==ROW()-1 -> 53

Sheet word
A1: 匹配内容 | B1: Lemma | C1: linked subtitle | D1: 翻译 | E1: 词性 | F1: 类别 | G1: ID
A2: Limonadenfabrik | B2: Limonadenfabrik | C2: ==IF(A2="","",IFERROR(HYPERLINK("#'subtitle'!A"&MATCH(TRUE,ISNUMBER(FIND(A2,subtitle!C:C)),0),INDEX(subtitle!C:C,MATCH(TRUE,ISNUMBER(FIND(A2,subtitle!C:C)),0))),"未找到（区分大小写）")) -> Michael ist Besitzer einer Limonadenfabrik. | D2: 柠檬水工厂 | E2: die | F2: n. | G2: ==IF(A2="","",IFERROR(INDEX(subtitle!E:E,MATCH(TRUE,ISNUMBER(FIND(A2,subtitle!C:C)),0)),"未找到")) -> 1
A3: Börse | B3: Börse | C3: ==IF(A3="","",IFERROR(HYPERLINK("#'subtitle'!A"&MATCH(TRUE,ISNUMBER(FIND(A3,subtitle!C:C)),0),INDEX(subtitle!C:C,MATCH(TRUE,ISNUMBER(FIND(A3,subtitle!C:C)),0))),"未找到（区分大小写）")) -> Mit seiner „Zitrus AG“ ist er vor 10 Jahren an die Börse gegangen | D3: 证券交易所 | E3: die | F3: n. | G3: ==IF(A3="","",IFERROR(INDEX(subtitle!E:E,MATCH(TRUE,ISNUMBER(FIND(A3,subtitle!C:C)),0)),"未找到")) -> 2
A4: vertreten | B4: vertreten | C4: ==IF(A4="","",IFERROR(HYPERLINK("#'subtitle'!A"&MATCH(TRUE,ISNUMBER(FIND(A4,subtitle!C:C)),0),INDEX(subtitle!C:C,MATCH(TRUE,ISNUMBER(FIND(A4,subtitle!C:C)),0))),"未找到（区分大小写）")) -> und seit neuestem auch im weltweiten Frucht-ETF vertreten. | D4: 被纳入 | F4: adj. | G4: ==IF(A4="","",IFERROR(INDEX(subtitle!E:E,MATCH(TRUE,ISNUMBER(FIND(A4,subtitle!C:C)),0)),"未找到")) -> 3
A5: Fonds | B5: Fonds | C5: ==IF(A5="","",IFERROR(HYPERLINK("#'subtitle'!A"&MATCH(TRUE,ISNUMBER(FIND(A5,subtitle!C:C)),0),INDEX(subtitle!C:C,MATCH(TRUE,ISNUMBER(FIND(A5,subtitle!C:C)),0))),"未找到（区分大小写）")) -> oder auf deutsch „börsengehandelter Fonds“ | D5: 基金 | E5: das | F5: n. | G5: ==IF(A5="","",IFERROR(INDEX(subtitle!E:E,MATCH(TRUE,ISNUMBER(FIND(A5,subtitle!C:C)),0)),"未找到")) -> 5
A6: bündelt | B6: bündeln | C6: ==IF(A6="","",IFERROR(HYPERLINK("#'subtitle'!A"&MATCH(TRUE,ISNUMBER(FIND(A6,subtitle!C:C)),0),INDEX(subtitle!C:C,MATCH(TRUE,ISNUMBER(FIND(A6,subtitle!C:C)),0))),"未找到（区分大小写）")) -> Ein ETF bündelt mehrere Anlageprodukte aus einem Bereich | D6: 组合 | F6: vt. | G6: ==IF(A6="","",IFERROR(INDEX(subtitle!E:E,MATCH(TRUE,ISNUMBER(FIND(A6,subtitle!C:C)),0)),"未找到")) -> 7
A7: Anlageprodukt | B7: Anlageprodukt | C7: ==IF(A7="","",IFERROR(HYPERLINK("#'subtitle'!A"&MATCH(TRUE,ISNUMBER(FIND(A7,subtitle!C:C)),0),INDEX(subtitle!C:C,MATCH(TRUE,ISNUMBER(FIND(A7,subtitle!C:C)),0))),"未找到（区分大小写）")) -> Ein ETF bündelt mehrere Anlageprodukte aus einem Bereich | D7: 投资产品 | E7: das | F7: n. | G7: ==IF(A7="","",IFERROR(INDEX(subtitle!E:E,MATCH(TRUE,ISNUMBER(FIND(A7,subtitle!C:C)),0)),"未找到")) -> 7
A8: bildet | B8: abbilden | C8: ==IF(A8="","",IFERROR(HYPERLINK("#'subtitle'!A"&MATCH(TRUE,ISNUMBER(FIND(A8,subtitle!C:C)),0),INDEX(subtitle!C:C,MATCH(TRUE,ISNUMBER(FIND(A8,subtitle!C:C)),0))),"未找到（区分大小写）")) -> und bildet deren Index ab | D8: 展现；呈现 | F8: vt.,trennbar | G8: ==IF(A8="","",IFERROR(INDEX(subtitle!E:E,MATCH(TRUE,ISNUMBER(FIND(A8,subtitle!C:C)),0)),"未找到")) -> 8
A9: Index | B9: Index | C9: ==IF(A9="","",IFERROR(HYPERLINK("#'subtitle'!A"&MATCH(TRUE,ISNUMBER(FIND(A9,subtitle!C:C)),0),INDEX(subtitle!C:C,MATCH(TRUE,ISNUMBER(FIND(A9,subtitle!C:C)),0))),"未找到（区分大小写）")) -> und bildet deren Index ab | D9: 指数；代码 | E9: der | F9: n. | G9: ==IF(A9="","",IFERROR(INDEX(subtitle!E:E,MATCH(TRUE,ISNUMBER(FIND(A9,subtitle!C:C)),0)),"未找到")) -> 8
A10: Aktienmarkt | B10: Aktienmarkt | C10: ==IF(A10="","",IFERROR(HYPERLINK("#'subtitle'!A"&MATCH(TRUE,ISNUMBER(FIND(A10,subtitle!C:C)),0),INDEX(subtitle!C:C,MATCH(TRUE,ISNUMBER(FIND(A10,subtitle!C:C)),0))),"未找到（区分大小写）")) -> Es gibt ETFs für den Aktienmarkt, | D10: 股票市场 | E10: der | F10: n. | G10: ==IF(A10="","",IFERROR(INDEX(subtitle!E:E,MATCH(TRUE,ISNUMBER(FIND(A10,subtitle!C:C)),0)),"未找到")) -> 10
A11: Anleihe | B11: Anleihe | C11: ==IF(A11="","",IFERROR(HYPERLINK("#'subtitle'!A"&MATCH(TRUE,ISNUMBER(FIND(A11,subtitle!C:C)),0),INDEX(subtitle!C:C,MATCH(TRUE,ISNUMBER(FIND(A11,subtitle!C:C)),0))),"未找到（区分大小写）")) -> für Anleihen, Rohstoffe oder sogar Immobilien. | D11: 债券 | E11: die | F11: n. | G11: ==IF(A11="","",IFERROR(INDEX(subtitle!E:E,MATCH(TRUE,ISNUMBER(FIND(A11,subtitle!C:C)),0)),"未找到")) -> 11
A12: Rohstoff | B12: Rohstoff | C12: ==IF(A12="","",IFERROR(HYPERLINK("#'subtitle'!A"&MATCH(TRUE,ISNUMBER(FIND(A12,subtitle!C:C)),0),INDEX(subtitle!C:C,MATCH(TRUE,ISNUMBER(FIND(A12,subtitle!C:C)),0))),"未找到（区分大小写）")) -> für Anleihen, Rohstoffe oder sogar Immobilien. | D12: 商品 | E12: der | F12: n. | G12: ==IF(A12="","",IFERROR(INDEX(subtitle!E:E,MATCH(TRUE,ISNUMBER(FIND(A12,subtitle!C:C)),0)),"未找到")) -> 11
A13: Immobilien | B13: Immobilien | C13: ==IF(A13="","",IFERROR(HYPERLINK("#'subtitle'!A"&MATCH(TRUE,ISNUMBER(FIND(A13,subtitle!C:C)),0),INDEX(subtitle!C:C,MATCH(TRUE,ISNUMBER(FIND(A13,subtitle!C:C)),0))),"未找到（区分大小写）")) -> für Anleihen, Rohstoffe oder sogar Immobilien. | D13: 房地产 | E13: pl. | F13: n. | G13: ==IF(A13="","",IFERROR(INDEX(subtitle!E:E,MATCH(TRUE,ISNUMBER(FIND(A13,subtitle!C:C)),0)),"未找到")) -> 11
A14: decken | B14: abdecken | C14: ==IF(A14="","",IFERROR(HYPERLINK("#'subtitle'!A"&MATCH(TRUE,ISNUMBER(FIND(A14,subtitle!C:C)),0),INDEX(subtitle!C:C,MATCH(TRUE,ISNUMBER(FIND(A14,subtitle!C:C)),0))),"未找到（区分大小写）")) -> Einige decken nur nachhaltige oder soziale Anlagen ab; | D14: 涵盖 | F14: vt.,trennbar | G14: ==IF(A14="","",IFERROR(INDEX(subtitle!E:E,MATCH(TRUE,ISNUMBER(FIND(A14,subtitle!C:C)),0)),"未找到")) -> 12
A15: Bündel | B15: Bündel | C15: ==IF(A15="","",IFERROR(HYPERLINK("#'subtitle'!A"&MATCH(TRUE,ISNUMBER(FIND(A15,subtitle!C:C)),0),INDEX(subtitle!C:C,MATCH(TRUE,ISNUMBER(FIND(A15,subtitle!C:C)),0))),"未找到（区分大小写）")) -> und die Wertentwicklung des ETF-Bündels sind dabei fast identisch. | D15: （ETF）组合 | E15: das | F15: n. | G15: ==IF(A15="","",IFERROR(INDEX(subtitle!E:E,MATCH(TRUE,ISNUMBER(FIND(A15,subtitle!C:C)),0)),"未找到")) -> 24
A16: manag | B16: managen | C16: ==IF(A16="","",IFERROR(HYPERLINK("#'subtitle'!A"&MATCH(TRUE,ISNUMBER(FIND(A16,subtitle!C:C)),0),INDEX(subtitle!C:C,MATCH(TRUE,ISNUMBER(FIND(A16,subtitle!C:C)),0))),"未找到（区分大小写）")) -> da ETFs nicht wie Fonds aktiv gemanagt werden, | D16: 管理 | F16: vt. | G16: ==IF(A16="","",IFERROR(INDEX(subtitle!E:E,MATCH(TRUE,ISNUMBER(FIND(A16,subtitle!C:C)),0)),"未找到")) -> 27
A17: greif | B17: eingreifen | C17: ==IF(A17="","",IFERROR(HYPERLINK("#'subtitle'!A"&MATCH(TRUE,ISNUMBER(FIND(A17,subtitle!C:C)),0),INDEX(subtitle!C:C,MATCH(TRUE,ISNUMBER(FIND(A17,subtitle!C:C)),0))),"未找到（区分大小写）")) -> Bei einem aktiv gemanagten Fonds greift ein Fondsmanager schneller ein | D17: 干预 | F17: vt.,trennbar | G17: ==IF(A17="","",IFERROR(INDEX(subtitle!E:E,MATCH(TRUE,ISNUMBER(FIND(A17,subtitle!C:C)),0)),"未找到")) -> 35
A18: ersetzen | B18: ersetzen | C18: ==IF(A18="","",IFERROR(HYPERLINK("#'subtitle'!A"&MATCH(TRUE,ISNUMBER(FIND(A18,subtitle!C:C)),0),INDEX(subtitle!C:C,MATCH(TRUE,ISNUMBER(FIND(A18,subtitle!C:C)),0))),"未找到（区分大小写）")) -> und kann die schlechtere Anlage z. B. durch ein anderes Produkt ersetzen. | D18: 替换 | F18: vt. | G18: ==IF(A18="","",IFERROR(INDEX(subtitle!E:E,MATCH(TRUE,ISNUMBER(FIND(A18,subtitle!C:C)),0)),"未找到")) -> 36
A19: Einbuße | B19: Einbuße | C19: ==IF(A19="","",IFERROR(HYPERLINK("#'subtitle'!A"&MATCH(TRUE,ISNUMBER(FIND(A19,subtitle!C:C)),0),INDEX(subtitle!C:C,MATCH(TRUE,ISNUMBER(FIND(A19,subtitle!C:C)),0))),"未找到（区分大小写）")) -> diese Einbuße mit den Kursen der anderen Firmen ausgeglichen werden. | D19: 损失 | E19: die | F19: n. | G19: ==IF(A19="","",IFERROR(INDEX(subtitle!E:E,MATCH(TRUE,ISNUMBER(FIND(A19,subtitle!C:C)),0)),"未找到")) -> 40
A20: spürbar | B20: spürbar | C20: ==IF(A20="","",IFERROR(HYPERLINK("#'subtitle'!A"&MATCH(TRUE,ISNUMBER(FIND(A20,subtitle!C:C)),0),INDEX(subtitle!C:C,MATCH(TRUE,ISNUMBER(FIND(A20,subtitle!C:C)),0))),"未找到（区分大小写）")) -> Und so ist der Verlust kaum spürbar. | D20: 显著的；可察觉的 | F20: adj. | G20: ==IF(A20="","",IFERROR(INDEX(subtitle!E:E,MATCH(TRUE,ISNUMBER(FIND(A20,subtitle!C:C)),0)),"未找到")) -> 41
A21: einsehen | B21: einsehen | C21: ==IF(A21="","",IFERROR(HYPERLINK("#'subtitle'!A"&MATCH(TRUE,ISNUMBER(FIND(A21,subtitle!C:C)),0),INDEX(subtitle!C:C,MATCH(TRUE,ISNUMBER(FIND(A21,subtitle!C:C)),0))),"未找到（区分大小写）")) -> außerdem kann Susanne jederzeit einsehen | D21: 查看 | F21: vt.,trennbar | G21: ==IF(A21="","",IFERROR(INDEX(subtitle!E:E,MATCH(TRUE,ISNUMBER(FIND(A21,subtitle!C:C)),0)),"未找到")) -> 42
A22: anlegt | B22: anlegen | C22: ==IF(A22="","",IFERROR(HYPERLINK("#'subtitle'!A"&MATCH(TRUE,ISNUMBER(FIND(A22,subtitle!C:C)),0),INDEX(subtitle!C:C,MATCH(TRUE,ISNUMBER(FIND(A22,subtitle!C:C)),0))),"未找到（区分大小写）")) -> und sich informieren, bevor sie ihr Geld anlegt. | D22: 投资 | F22: vt.,trennbar | G22: ==IF(A22="","",IFERROR(INDEX(subtitle!E:E,MATCH(TRUE,ISNUMBER(FIND(A22,subtitle!C:C)),0)),"未找到")) -> 51

Sheet expression
A1: 匹配内容 | B1: 原型 | C1: linked subtitle | D1: 翻译 | E1: ID
A2: anteilig | B2: anteilig verteilt | C2: ==IF(A2="","",IFERROR(HYPERLINK("#'subtitle'!A"&MATCH(TRUE,ISNUMBER(FIND(A2,subtitle!C:C)),0),INDEX(subtitle!C:C,MATCH(TRUE,ISNUMBER(FIND(A2,subtitle!C:C)),0))),"未找到（区分大小写）")) -> wobei ihr Investment anteilig auf alle enthaltenen Anlagen verteilt wird. | D2: 按份额分配 | E2: ==IF(A2="","",IFERROR(INDEX(subtitle!E:E,MATCH(TRUE,ISNUMBER(FIND(A2,subtitle!C2:C500)),0)+1),"未找到")) -> 22
A3: spricht | B3: von ... sprechen | C3: ==IF(A3="","",IFERROR(HYPERLINK("#'subtitle'!A"&MATCH(TRUE,ISNUMBER(FIND(A3,subtitle!C:C)),0),INDEX(subtitle!C:C,MATCH(TRUE,ISNUMBER(FIND(A3,subtitle!C:C)),0))),"未找到（区分大小写）")) -> Investiert man in einen ETF, spricht man auch von einem „passiven“ Investment, | D3: 称之为 | E3: ==IF(A3="","",IFERROR(INDEX(subtitle!E:E,MATCH(TRUE,ISNUMBER(FIND(A3,subtitle!C3:C501)),0)+1),"未找到")) -> 25
A4: automatisiert | B4: automatisiert ablaufen | C4: ==IF(A4="","",IFERROR(HYPERLINK("#'subtitle'!A"&MATCH(TRUE,ISNUMBER(FIND(A4,subtitle!C:C)),0),INDEX(subtitle!C:C,MATCH(TRUE,ISNUMBER(FIND(A4,subtitle!C:C)),0))),"未找到（区分大小写）")) -> sondern vieles automatisiert abläuft. | D4: 自动进行 | E4: ==IF(A4="","",IFERROR(INDEX(subtitle!E:E,MATCH(TRUE,ISNUMBER(FIND(A4,subtitle!C4:C502)),0)+1),"未找到")) -> 26

Sheet exercise
A1: question_type | B1: question_id | C1: question | D1: answer | E1: is_correct | F1: explanation
A2: Richtig oder Falsch | B2: 1 | C2: ETFs werden aktiv von Fondsmanagern gesteuert, weshalb sie höhere Gebühren verursachen als andere Fonds. | D2: Richtig | E2: FALSE | F2: 错误。原文提到 ETF 是“被动投资”（passives Investment），且“nicht wie Fonds aktiv gemanagt”（不像基金那样被主动管理），因此 Susanne 支付的费用是“weniger Gebühren”（更少的费用），而不是更高。
A3: Richtig oder Falsch | B3: 1 | C3: ETFs werden aktiv von Fondsmanagern gesteuert, weshalb sie höhere Gebühren verursachen als andere Fonds. | D3: Falsch | E3: TRUE | F3: 正确。原文指出 ETF 流程自动化，不像主动基金那样管理，因此费用较低。
A4: Richtig oder Falsch | B4: 2 | C4: Das Investieren in ETFs ist flexibel: Es gibt keine Mindestlaufzeit und sie können täglich gehandelt werden. | D4: Richtig | E4: TRUE | F4: 正确。原文明确说道：“ETFs können täglich gehandelt werden und es gibt keine Mindestlaufzeit”（ETF可以每天交易且无最短期限）。
A5: Richtig oder Falsch | B5: 2 | C5: Das Investieren in ETFs ist flexibel: Es gibt keine Mindestlaufzeit und sie können täglich gehandelt werden. | D5: Falsch | E5: FALSE | F5: 错误。原文明确指出 ETF 交易非常灵活，没有这些限制。
A6: Wählen Sie aus | B6: 3 | C6: Welchen Vorteil hat Susanne finanziell, wenn sie in einen ETF statt in einzelne Aktien investiert? | D6: (a) Sie besitzt dann automatisch die ganze Firma Zitrus AG. | E6: FALSE | F6: 错误。ETF 包含的是“Anteile”（股份），并不代表拥有整个公司。
A7: Wählen Sie aus | B7: 3 | C7: Welchen Vorteil hat Susanne finanziell, wenn sie in einen ETF statt in einzelne Aktien investiert? | D7: (b) Sie zahlt weniger Gebühren, da der ETF passiv und automatisiert läuft. | E7: TRUE | F7: 正确。原文解释说，由于流程自动化（automatisiert abläuft），Susanne 支付的费用比主动管理基金要少（zahlt ... weniger Gebühren）。
A8: Wählen Sie aus | B8: 3 | C8: Welchen Vorteil hat Susanne finanziell, wenn sie in einen ETF statt in einzelne Aktien investiert? | D8: (c) Sie bekommt garantiert jeden Monat 25 Euro geschenkt. | E8: FALSE | F8: 错误。原文中“ab 25 Euro monatlich”指的是投资门槛（每月25欧元起），而不是赠送现金。
A9: Wählen Sie aus | B9: 4 | C9: Was passiert laut Text, wenn bei einem ETF mit 1000 Firmen der Kurs einer einzigen Firma sinkt? | D9: (a) Der gesamte ETF verliert sofort massiv an Wert. | E9: FALSE | F9: 错误。原文提到因为包含很多公司，单一公司的损失“kaum spürbar”（几乎感觉不到）。
A10: Wählen Sie aus | B10: 4 | C10: Was passiert laut Text, wenn bei einem ETF mit 1001 Firmen der Kurs einer einzigen Firma sinkt? | D10: (b) Der ETF wird sofort vom Markt genommen und geschlossen. | E10: FALSE | F10: 错误。视频中未提及这种情况。
A11: Wählen Sie aus | B11: 4 | C11: Was passiert laut Text, wenn bei einem ETF mit 1002 Firmen der Kurs einer einzigen Firma sinkt? | D11: (c) Der Verlust ist kaum spürbar, da er durch andere Firmen ausgeglichen wird | E11: TRUE | F11: 正确。原文解释说，亏损会被其他公司的股价“ausgeglichen”（抵消），因此“ist der Verlust kaum spürbar”（损失几乎感觉不到）。
